pytest_fluentbit/__init__.py
pytest_fluentbit/additional_information.py
pytest_fluentbit/plugin.py
pytest_fluentbit/test_report.py
pytest_fluentbit-0.1.5.dist-info/LICENSE
pytest_fluentbit-0.1.5.dist-info/METADATA
pytest_fluentbit-0.1.5.dist-info/WHEEL
pytest_fluentbit-0.1.5.dist-info/entry_points.txt
pytest_fluentbit-0.1.5.dist-info/top_level.txt
pytest_fluentbit-0.1.5.dist-info/RECORD
