Metadata-Version: 2.1
Name: pytest-fluentbit
Version: 0.1.5
Summary: A pytest plugin in order to provide logs via fluentbit
Author-email: Sujay Kanungo <sujay.kanungo@gmail.com>
License: MIT
Project-URL: project, https://github.com/sujay2002/pytest-fluentbit
Keywords: pytest,logging,fluent
Platform: Unix
Platform: Linux
Platform: Windows
Classifier: Development Status :: 4 - Beta
Classifier: Intended Audience :: Developers
Classifier: Intended Audience :: Science/Research
Classifier: License :: OSI Approved :: MIT License
Classifier: Operating System :: Microsoft :: Windows
Classifier: Operating System :: POSIX :: Linux
Classifier: Operating System :: MacOS :: MacOS X
Classifier: Programming Language :: Python
Classifier: Topic :: Scientific/Engineering :: Interface Engine/Protocol Translator
Classifier: Topic :: Software Development :: Libraries :: Python Modules
Classifier: Programming Language :: Python :: 3.8
Classifier: Programming Language :: Python :: 3.9
Classifier: Programming Language :: Python :: 3.10
Classifier: Framework :: Pytest
Requires-Python: >=3.7
License-File: LICENSE
Requires-Dist: pytest (>=7.0.0)
Requires-Dist: msgpack
Requires-Dist: six
Requires-Dist: fluent-logger
Provides-Extra: docs
Requires-Dist: sphinx ; extra == 'docs'
Requires-Dist: sphinx-rtd-theme ; extra == 'docs'
Requires-Dist: myst-parser ; extra == 'docs'
Provides-Extra: test
Requires-Dist: pytest ; extra == 'test'
Requires-Dist: coverage[toml] ; extra == 'test'
Requires-Dist: pytest-cov ; extra == 'test'
Requires-Dist: pytest-xdist[psutil] ; extra == 'test'
Requires-Dist: six ; extra == 'test'
